throwcolour/__init__.py
throwcolour-1.0.7.dist-info/LICENSE
throwcolour-1.0.7.dist-info/METADATA
throwcolour-1.0.7.dist-info/WHEEL
throwcolour-1.0.7.dist-info/top_level.txt
throwcolour-1.0.7.dist-info/RECORD
